<?xml version="1.0"?>
<parq>
	<parquimetro codigo="55555">
		<rua>RuaR</rua>
		<numero>123123</numero>
		<cidade>Cidade C </cidade>
		<estado>Estado E </estado>
		<pais>Pais P</pais>
		<horaInicio>08:30:00</horaInicio>
		<horaFinal>18:30:00</horaFinal>
		<tempoMin>PT30M</tempoMin>
		<tempoMax>PT2H</tempoMax>
		<incremento>PT10M</incremento>
		<valorIncremento>0.25</valorIncremento>
		<CINCO>Y</CINCO>
		<DEZ>Y</DEZ>
		<VINTEECINCO>N</VINTEECINCO>
		<CINQUENTA>N</CINQUENTA>
		<CEM>Y</CEM>		
	</parquimetro>
</parq>